slovakrailways/__init__.py
slovakrailways/cache.py
slovakrailways/common.py
slovakrailways/departure.py
slovakrailways/meta.py
slovakrailways/route.py
slovakrailways/station.py
slovakrailways/train.py
slovakrailways/data/uic.csv
slovakrailways-0.1.0.dist-info/LICENSE
slovakrailways-0.1.0.dist-info/METADATA
slovakrailways-0.1.0.dist-info/WHEEL
slovakrailways-0.1.0.dist-info/top_level.txt
slovakrailways-0.1.0.dist-info/RECORD
